guardian_clients/__init__.py
guardian_clients/_version.py
guardian_clients/python/__init__.py
guardian_clients/python/api.py
guardian_clients/python/credentials.py
guardian_clients/python/guardian.py
guardian_clients-0.0.0.31.dist-info/METADATA
guardian_clients-0.0.0.31.dist-info/WHEEL
guardian_clients-0.0.0.31.dist-info/entry_points.txt
guardian_clients-0.0.0.31.dist-info/RECORD
