Metadata-Version: 2.1
Name: guardian-clients
Version: 0.0.0.31
Summary: Reference client implementations for Guardian product - SDKs, CLIs, CURL scripts, etc.
License: Apache-2.0
Author: ProtectAI
Author-email: community@protectai.com
Requires-Python: >=3.9,<3.12
Classifier: License :: OSI Approved :: Apache Software License
Classifier: Programming Language :: Python :: 3
Classifier: Programming Language :: Python :: 3.9
Classifier: Programming Language :: Python :: 3.10
Classifier: Programming Language :: Python :: 3.11
Requires-Dist: click (>=8.1.7,<9.0.0)
Requires-Dist: pyjwt (>=2.8.0,<3.0.0)
Requires-Dist: requests (>=2.30.0,<3.0.0)
